<?xml version='1.0' encoding='ISO-8859-1'?>
<trace type='processor' name='Adreno (FCFS)'>
  <start task='Task3' iteration='0' time='0.000472851284051282'>
  </start>  <contextswitch task='Task3' time='0.000480124011324009'>
  </contextswitch>  <stop task='Task3' time='0.000996487647687646'>
  </stop>  <start task='Task7' iteration='0' time='0.00100672764768765'>
  </start>  <contextswitch task='Task7' time='0.00101400037496037'>
  </contextswitch>  <stop task='Task7' time='0.00173803673859674'>
  </stop>  <start task='Task3' iteration='1' time='0.00247285128205128'>
  </start>  <contextswitch task='Task3' time='0.00248012400932401'>
  </contextswitch>  <stop task='Task3' time='0.00299648764568765'>
  </stop>  <start task='Task7' iteration='1' time='0.00300672764568765'>
  </start>  <contextswitch task='Task7' time='0.00301400037296037'>
  </contextswitch>  <stop task='Task7' time='0.00373803673659674'>
  </stop>  <start task='Task3' iteration='2' time='0.00447285128205128'>
  </start>  <contextswitch task='Task3' time='0.00448012400932401'>
  </contextswitch>  <stop task='Task3' time='0.00507932400932401'>
  </stop>  <start task='Task7' iteration='2' time='0.00508956400932401'>
  </start>  <contextswitch task='Task7' time='0.00509683673659674'>
  </contextswitch>  <stop task='Task7' time='0.00564338219114219'>
  </stop>  <start task='Task3' iteration='3' time='0.00647285128205128'>
  </start>  <contextswitch task='Task3' time='0.00648012400932401'>
  </contextswitch>  <stop task='Task3' time='0.00699648764568764'>
  </stop>  <start task='Task7' iteration='3' time='0.00700672764568764'>
  </start>  <contextswitch task='Task7' time='0.00701400037296037'>
  </contextswitch>  <stop task='Task7' time='0.00773803673659674'>
  </stop>  <start task='Task3' iteration='4' time='0.00847285128205128'>
  </start>  <contextswitch task='Task3' time='0.00848012400932401'>
  </contextswitch>  <stop task='Task3' time='0.00907932400932401'>
  </stop>  <start task='Task7' iteration='4' time='0.00908956400932401'>
  </start>  <contextswitch task='Task7' time='0.00909683673659674'>
  </contextswitch>  <stop task='Task7' time='0.00964338219114219'>
  </stop>  <start task='Task3' iteration='5' time='0.0104728512820513'>
  </start>  <contextswitch task='Task3' time='0.010480124009324'>
  </contextswitch>  <stop task='Task3' time='0.011079324009324'>
  </stop>  <start task='Task7' iteration='5' time='0.011089564009324'>
  </start>  <contextswitch task='Task7' time='0.0110968367365967'>
  </contextswitch>  <stop task='Task7' time='0.0116433821911422'>
  </stop>  <start task='Task3' iteration='6' time='0.0124728512820513'>
  </start>  <contextswitch task='Task3' time='0.012480124009324'>
  </contextswitch>  <stop task='Task3' time='0.013079324009324'>
  </stop>  <start task='Task7' iteration='6' time='0.013089564009324'>
  </start>  <contextswitch task='Task7' time='0.0130968367365967'>
  </contextswitch>  <stop task='Task7' time='0.0136433821911422'>
  </stop>  <start task='Task3' iteration='7' time='0.0144728512820513'>
  </start>  <contextswitch task='Task3' time='0.014480124009324'>
  </contextswitch>  <stop task='Task3' time='0.0149964876456876'>
  </stop>  <start task='Task7' iteration='7' time='0.0150067276456876'>
  </start>  <contextswitch task='Task7' time='0.0150140003729604'>
  </contextswitch>  <stop task='Task7' time='0.0157380367365967'>
  </stop>  <start task='Task3' iteration='8' time='0.0164728512820513'>
  </start>  <contextswitch task='Task3' time='0.016480124009324'>
  </contextswitch>  <stop task='Task3' time='0.017079324009324'>
  </stop>  <start task='Task7' iteration='8' time='0.017089564009324'>
  </start>  <contextswitch task='Task7' time='0.0170968367365967'>
  </contextswitch>  <stop task='Task7' time='0.0176433821911422'>
  </stop>  <start task='Task3' iteration='9' time='0.0184728512820513'>
  </start>  <contextswitch task='Task3' time='0.018480124009324'>
  </contextswitch>  <stop task='Task3' time='0.019079324009324'>
  </stop>  <start task='Task7' iteration='9' time='0.019089564009324'>
  </start>  <contextswitch task='Task7' time='0.0190968367365967'>
  </contextswitch>  <stop task='Task7' time='0.0196433821911422'>
  </stop>  <start task='Task3' iteration='10' time='0.0204728512820513'>
  </start>  <contextswitch task='Task3' time='0.020480124009324'>
  </contextswitch>  <stop task='Task3' time='0.021079324009324'>
  </stop>  <start task='Task7' iteration='10' time='0.021089564009324'>
  </start>  <contextswitch task='Task7' time='0.0210968367365967'>
  </contextswitch>  <stop task='Task7' time='0.0216433821911422'>
  </stop>  <start task='Task3' iteration='11' time='0.0224728512820513'>
  </start>  <contextswitch task='Task3' time='0.022480124009324'>
  </contextswitch>  <stop task='Task3' time='0.023079324009324'>
  </stop>  <start task='Task7' iteration='11' time='0.023089564009324'>
  </start>  <contextswitch task='Task7' time='0.0230968367365967'>
  </contextswitch>  <stop task='Task7' time='0.0236433821911422'>
  </stop>  <start task='Task3' iteration='12' time='0.0244728512820513'>
  </start>  <contextswitch task='Task3' time='0.024480124009324'>
  </contextswitch>  <stop task='Task3' time='0.025079324009324'>
  </stop>  <start task='Task7' iteration='12' time='0.025089564009324'>
  </start>  <contextswitch task='Task7' time='0.0250968367365967'>
  </contextswitch>  <stop task='Task7' time='0.0256433821911422'>
  </stop>  <start task='Task3' iteration='13' time='0.0264728512820513'>
  </start>  <contextswitch task='Task3' time='0.026480124009324'>
  </contextswitch>  <stop task='Task3' time='0.0269964876456877'>
  </stop>  <start task='Task7' iteration='13' time='0.0270067276456877'>
  </start>  <contextswitch task='Task7' time='0.0270140003729604'>
  </contextswitch>  <stop task='Task7' time='0.0277380367365967'>
  </stop>  <start task='Task3' iteration='14' time='0.0284728512820513'>
  </start>  <contextswitch task='Task3' time='0.028480124009324'>
  </contextswitch>  <stop task='Task3' time='0.0289964876456876'>
  </stop>  <start task='Task7' iteration='14' time='0.0290067276456876'>
  </start>  <contextswitch task='Task7' time='0.0290140003729604'>
  </contextswitch>  <stop task='Task7' time='0.0297380367365967'>
  </stop>  <start task='Task3' iteration='15' time='0.0304728512820513'>
  </start>  <contextswitch task='Task3' time='0.030480124009324'>
  </contextswitch>  <stop task='Task3' time='0.0309964876456876'>
  </stop>  <start task='Task7' iteration='15' time='0.0310067276456877'>
  </start>  <contextswitch task='Task7' time='0.0310140003729604'>
  </contextswitch>  <stop task='Task7' time='0.0317380367365967'>
  </stop>  <start task='Task3' iteration='16' time='0.0324728512820513'>
  </start>  <contextswitch task='Task3' time='0.032480124009324'>
  </contextswitch>  <stop task='Task3' time='0.0329964876456876'>
  </stop>  <start task='Task7' iteration='16' time='0.0330067276456876'>
  </start>  <contextswitch task='Task7' time='0.0330140003729604'>
  </contextswitch>  <stop task='Task7' time='0.0337380367365967'>
  </stop>  <start task='Task3' iteration='17' time='0.0344728512820513'>
  </start>  <contextswitch task='Task3' time='0.034480124009324'>
  </contextswitch>  <stop task='Task3' time='0.0349964876456876'>
  </stop>  <start task='Task7' iteration='17' time='0.0350067276456876'>
  </start>  <contextswitch task='Task7' time='0.0350140003729604'>
  </contextswitch>  <stop task='Task7' time='0.0357380367365967'>
  </stop>  <start task='Task3' iteration='18' time='0.0364728512820513'>
  </start>  <contextswitch task='Task3' time='0.036480124009324'>
  </contextswitch>  <stop task='Task3' time='0.0369964876456876'>
  </stop>  <start task='Task7' iteration='18' time='0.0370067276456876'>
  </start>  <contextswitch task='Task7' time='0.0370140003729604'>
  </contextswitch>  <stop task='Task7' time='0.0377380367365967'>
  </stop>  <start task='Task3' iteration='19' time='0.0384728512820513'>
  </start>  <contextswitch task='Task3' time='0.038480124009324'>
  </contextswitch>  <stop task='Task3' time='0.0389964876456876'>
  </stop>  <start task='Task7' iteration='19' time='0.0390067276456876'>
  </start>  <contextswitch task='Task7' time='0.0390140003729604'>
  </contextswitch>  <stop task='Task7' time='0.0397380367365967'>
  </stop>  <start task='Task3' iteration='20' time='0.0404728512820513'>
  </start>  <contextswitch task='Task3' time='0.040480124009324'>
  </contextswitch>  <stop task='Task3' time='0.0409964876456876'>
  </stop>  <start task='Task7' iteration='20' time='0.0410067276456876'>
  </start>  <contextswitch task='Task7' time='0.0410140003729604'>
  </contextswitch>  <stop task='Task7' time='0.0417380367365967'>
  </stop>  <start task='Task3' iteration='21' time='0.0424728512820513'>
  </start>  <contextswitch task='Task3' time='0.042480124009324'>
  </contextswitch>  <stop task='Task3' time='0.0429964876456876'>
  </stop>  <start task='Task7' iteration='21' time='0.0430067276456876'>
  </start>  <contextswitch task='Task7' time='0.0430140003729604'>
  </contextswitch>  <stop task='Task7' time='0.0437380367365967'>
  </stop>  <start task='Task3' iteration='22' time='0.0444728512820513'>
  </start>  <contextswitch task='Task3' time='0.044480124009324'>
  </contextswitch>  <stop task='Task3' time='0.0449964876456876'>
  </stop>  <start task='Task7' iteration='22' time='0.0450067276456876'>
  </start>  <contextswitch task='Task7' time='0.0450140003729604'>
  </contextswitch>  <stop task='Task7' time='0.0457380367365967'>
  </stop>  <start task='Task3' iteration='23' time='0.0464728512820513'>
  </start>  <contextswitch task='Task3' time='0.046480124009324'>
  </contextswitch>  <stop task='Task3' time='0.0469964876456876'>
  </stop>  <start task='Task7' iteration='23' time='0.0470067276456876'>
  </start>  <contextswitch task='Task7' time='0.0470140003729604'>
  </contextswitch>  <stop task='Task7' time='0.0477380367365967'>
  </stop>  <start task='Task3' iteration='24' time='0.0484728512820513'>
  </start>  <contextswitch task='Task3' time='0.048480124009324'>
  </contextswitch>  <stop task='Task3' time='0.0489964876456876'>
  </stop>  <start task='Task7' iteration='24' time='0.0490067276456876'>
  </start>  <contextswitch task='Task7' time='0.0490140003729604'>
  </contextswitch>  <stop task='Task7' time='0.0497380367365967'>
  </stop>  <start task='Task3' iteration='25' time='0.0504728512820513'>
  </start>  <contextswitch task='Task3' time='0.050480124009324'>
  </contextswitch>  <stop task='Task3' time='0.0509964876456876'>
  </stop>  <start task='Task7' iteration='25' time='0.0510067276456876'>
  </start>  <contextswitch task='Task7' time='0.0510140003729604'>
  </contextswitch>  <stop task='Task7' time='0.0517380367365967'>
  </stop>  <start task='Task3' iteration='26' time='0.0524728512820513'>
  </start>  <contextswitch task='Task3' time='0.052480124009324'>
  </contextswitch>  <stop task='Task3' time='0.0529964876456876'>
  </stop>  <start task='Task7' iteration='26' time='0.0530067276456876'>
  </start>  <contextswitch task='Task7' time='0.0530140003729604'>
  </contextswitch>  <stop task='Task7' time='0.0537380367365967'>
  </stop>  <start task='Task3' iteration='27' time='0.0544728512820513'>
  </start>  <contextswitch task='Task3' time='0.054480124009324'>
  </contextswitch>  <stop task='Task3' time='0.0549964876456876'>
  </stop>  <start task='Task7' iteration='27' time='0.0550067276456876'>
  </start>  <contextswitch task='Task7' time='0.0550140003729604'>
  </contextswitch>  <stop task='Task7' time='0.0557380367365967'>
  </stop>  <start task='Task3' iteration='28' time='0.0564728512820513'>
  </start>  <contextswitch task='Task3' time='0.056480124009324'>
  </contextswitch>  <stop task='Task3' time='0.057079324009324'>
  </stop>  <start task='Task7' iteration='28' time='0.057089564009324'>
  </start>  <contextswitch task='Task7' time='0.0570968367365967'>
  </contextswitch>  <stop task='Task7' time='0.0576433821911422'>
  </stop>  <start task='Task3' iteration='29' time='0.0584728512820513'>
  </start>  <contextswitch task='Task3' time='0.058480124009324'>
  </contextswitch>  <stop task='Task3' time='0.059079324009324'>
  </stop>  <start task='Task7' iteration='29' time='0.059089564009324'>
  </start>  <contextswitch task='Task7' time='0.0590968367365967'>
  </contextswitch>  <stop task='Task7' time='0.0596433821911422'>
  </stop>  <start task='Task3' iteration='30' time='0.0604728512820513'>
  </start>  <contextswitch task='Task3' time='0.060480124009324'>
  </contextswitch>  <stop task='Task3' time='0.0609964876456876'>
  </stop>  <start task='Task7' iteration='30' time='0.0610067276456876'>
  </start>  <contextswitch task='Task7' time='0.0610140003729604'>
  </contextswitch>  <stop task='Task7' time='0.0617380367365967'>
  </stop>  <start task='Task3' iteration='31' time='0.0624728512820513'>
  </start>  <contextswitch task='Task3' time='0.062480124009324'>
  </contextswitch>  <stop task='Task3' time='0.0629964876456876'>
  </stop>  <start task='Task7' iteration='31' time='0.0630067276456876'>
  </start>  <contextswitch task='Task7' time='0.0630140003729604'>
  </contextswitch>  <stop task='Task7' time='0.0637380367365967'>
  </stop>  <start task='Task3' iteration='32' time='0.0644728512820513'>
  </start>  <contextswitch task='Task3' time='0.064480124009324'>
  </contextswitch>  <stop task='Task3' time='0.0649964876456876'>
  </stop>  <start task='Task7' iteration='32' time='0.0650067276456876'>
  </start>  <contextswitch task='Task7' time='0.0650140003729604'>
  </contextswitch>  <stop task='Task7' time='0.0657380367365967'>
  </stop>  <start task='Task3' iteration='33' time='0.0664728512820513'>
  </start>  <contextswitch task='Task3' time='0.066480124009324'>
  </contextswitch>  <stop task='Task3' time='0.0669964876456877'>
  </stop>  <start task='Task7' iteration='33' time='0.0670067276456876'>
  </start>  <contextswitch task='Task7' time='0.0670140003729604'>
  </contextswitch>  <stop task='Task7' time='0.0677380367365967'>
  </stop>  <start task='Task3' iteration='34' time='0.0684728512820513'>
  </start>  <contextswitch task='Task3' time='0.068480124009324'>
  </contextswitch>  <stop task='Task3' time='0.0689964876456877'>
  </stop>  <start task='Task7' iteration='34' time='0.0690067276456876'>
  </start>  <contextswitch task='Task7' time='0.0690140003729604'>
  </contextswitch>  <stop task='Task7' time='0.0697380367365967'>
  </stop>  <start task='Task3' iteration='35' time='0.0704728512820513'>
  </start>  <contextswitch task='Task3' time='0.070480124009324'>
  </contextswitch>  <stop task='Task3' time='0.071079324009324'>
  </stop>  <start task='Task7' iteration='35' time='0.071089564009324'>
  </start>  <contextswitch task='Task7' time='0.0710968367365967'>
  </contextswitch>  <stop task='Task7' time='0.0716433821911422'>
  </stop>  <start task='Task3' iteration='36' time='0.0724728512820513'>
  </start>  <contextswitch task='Task3' time='0.072480124009324'>
  </contextswitch>  <stop task='Task3' time='0.073079324009324'>
  </stop>  <start task='Task7' iteration='36' time='0.073089564009324'>
  </start>  <contextswitch task='Task7' time='0.0730968367365967'>
  </contextswitch>  <stop task='Task7' time='0.0736433821911422'>
  </stop>  <start task='Task3' iteration='37' time='0.0744728512820513'>
  </start>  <contextswitch task='Task3' time='0.074480124009324'>
  </contextswitch>  <stop task='Task3' time='0.0749964876456876'>
  </stop>  <start task='Task7' iteration='37' time='0.0750067276456876'>
  </start>  <contextswitch task='Task7' time='0.0750140003729604'>
  </contextswitch>  <stop task='Task7' time='0.0757380367365967'>
  </stop>  <start task='Task3' iteration='38' time='0.0764728512820513'>
  </start>  <contextswitch task='Task3' time='0.076480124009324'>
  </contextswitch>  <stop task='Task3' time='0.0769964876456876'>
  </stop>  <start task='Task7' iteration='38' time='0.0770067276456876'>
  </start>  <contextswitch task='Task7' time='0.0770140003729604'>
  </contextswitch>  <stop task='Task7' time='0.0777380367365967'>
  </stop>  <start task='Task3' iteration='39' time='0.0784728512820513'>
  </start>  <contextswitch task='Task3' time='0.078480124009324'>
  </contextswitch>  <stop task='Task3' time='0.079079324009324'>
  </stop>  <start task='Task7' iteration='39' time='0.079089564009324'>
  </start>  <contextswitch task='Task7' time='0.0790968367365967'>
  </contextswitch>  <stop task='Task7' time='0.0796433821911422'>
  </stop>  <start task='Task3' iteration='40' time='0.0804728512820513'>
  </start>  <contextswitch task='Task3' time='0.080480124009324'>
  </contextswitch>  <stop task='Task3' time='0.081079324009324'>
  </stop>  <start task='Task7' iteration='40' time='0.081089564009324'>
  </start>  <contextswitch task='Task7' time='0.0810968367365967'>
  </contextswitch>  <stop task='Task7' time='0.0816433821911422'>
  </stop>  <start task='Task3' iteration='41' time='0.0824728512820513'>
  </start>  <contextswitch task='Task3' time='0.082480124009324'>
  </contextswitch>  <stop task='Task3' time='0.0829964876456877'>
  </stop>  <start task='Task7' iteration='41' time='0.0830067276456876'>
  </start>  <contextswitch task='Task7' time='0.0830140003729604'>
  </contextswitch>  <stop task='Task7' time='0.0837380367365967'>
  </stop>  <start task='Task3' iteration='42' time='0.0844728512820513'>
  </start>  <contextswitch task='Task3' time='0.084480124009324'>
  </contextswitch>  <stop task='Task3' time='0.085079324009324'>
  </stop>  <start task='Task7' iteration='42' time='0.085089564009324'>
  </start>  <contextswitch task='Task7' time='0.0850968367365967'>
  </contextswitch>  <stop task='Task7' time='0.0856433821911422'>
  </stop>  <start task='Task3' iteration='43' time='0.0864728512820513'>
  </start>  <contextswitch task='Task3' time='0.086480124009324'>
  </contextswitch>  <stop task='Task3' time='0.0869964876456877'>
  </stop>  <start task='Task7' iteration='43' time='0.0870067276456876'>
  </start>  <contextswitch task='Task7' time='0.0870140003729604'>
  </contextswitch>  <stop task='Task7' time='0.0877380367365967'>
  </stop>  <start task='Task3' iteration='44' time='0.0884728512820513'>
  </start>  <contextswitch task='Task3' time='0.088480124009324'>
  </contextswitch>  <stop task='Task3' time='0.0889964876456876'>
  </stop>  <start task='Task7' iteration='44' time='0.0890067276456876'>
  </start>  <contextswitch task='Task7' time='0.0890140003729604'>
  </contextswitch>  <stop task='Task7' time='0.0897380367365967'>
  </stop>  <start task='Task3' iteration='45' time='0.0904728512820513'>
  </start>  <contextswitch task='Task3' time='0.090480124009324'>
  </contextswitch>  <stop task='Task3' time='0.0909964876456876'>
  </stop>  <start task='Task7' iteration='45' time='0.0910067276456876'>
  </start>  <contextswitch task='Task7' time='0.0910140003729604'>
  </contextswitch>  <stop task='Task7' time='0.0917380367365967'>
  </stop>  <start task='Task3' iteration='46' time='0.0924728512820513'>
  </start>  <contextswitch task='Task3' time='0.092480124009324'>
  </contextswitch>  <stop task='Task3' time='0.0929964876456876'>
  </stop>  <start task='Task7' iteration='46' time='0.0930067276456876'>
  </start>  <contextswitch task='Task7' time='0.0930140003729604'>
  </contextswitch>  <stop task='Task7' time='0.0937380367365967'>
  </stop>  <start task='Task3' iteration='47' time='0.0944728512820513'>
  </start>  <contextswitch task='Task3' time='0.094480124009324'>
  </contextswitch>  <stop task='Task3' time='0.095079324009324'>
  </stop>  <start task='Task7' iteration='47' time='0.095089564009324'>
  </start>  <contextswitch task='Task7' time='0.0950968367365967'>
  </contextswitch>  <stop task='Task7' time='0.0956433821911422'>
  </stop>  <start task='Task3' iteration='48' time='0.0964728512820513'>
  </start>  <contextswitch task='Task3' time='0.096480124009324'>
  </contextswitch>  <stop task='Task3' time='0.0969964876456876'>
  </stop>  <start task='Task7' iteration='48' time='0.0970067276456876'>
  </start>  <contextswitch task='Task7' time='0.0970140003729604'>
  </contextswitch>  <stop task='Task7' time='0.0977380367365967'>
  </stop>  <start task='Task3' iteration='49' time='0.0984728512820513'>
  </start>  <contextswitch task='Task3' time='0.098480124009324'>
  </contextswitch>  <stop task='Task3' time='0.0989964876456877'>
  </stop>  <start task='Task7' iteration='49' time='0.0990067276456876'>
  </start>  <contextswitch task='Task7' time='0.0990140003729604'>
  </contextswitch>  <stop task='Task7' time='0.0997380367365967'>
  </stop>  <start task='Task3' iteration='50' time='0.100472851282051'>
  </start></trace>